{
  "actions": {
    "path": "data/assets/actions.json"
  },
  "activities": {
    "path": "data/assets/activities.json"
  },
  "enemies": {
    "path": "data/assets/enemies.json"
  },
  "fonts": {
    "path": "data/assets/fonts.json"
  },
  "game": {
    "path": "data/assets/game.json"
  },
  "hero": {
    "path": "data/assets/hero.json"
  },
  "textures": {
    "path": "data/assets/textures.json"
  },
  "widgetsMenu": {
    "path": "data/assets/widgetsMenu.json"
  },
  "widgetsActivity": {
    "path": "data/assets/widgetsActivity.json"
  }

}